ssh_client/__init__.py
ssh_client/config.py
ssh_client/main.py
ssh_client/remote_client.py
ssh_client/test.py
tests/__init__.py
ssh_client-0.1.0.dist-info/METADATA
ssh_client-0.1.0.dist-info/WHEEL
ssh_client-0.1.0.dist-info/top_level.txt
ssh_client-0.1.0.dist-info/RECORD
