Metadata-Version: 2.1
Name: ssh-client
Version: 0.1.0
Summary: Perform operations in client
Home-page: UNKNOWN
Author: Diego
Author-email: diego@test.com
License: MIT
Platform: UNKNOWN
Requires-Python: >=3.7.7
